LICENSE
MANIFEST.in
README.md
setup.py
elasticmodels/__init__.py
elasticmodels/forms.py
elasticmodels/models.py
elasticmodels/tests.py
elasticmodels.egg-info/PKG-INFO
elasticmodels.egg-info/SOURCES.txt
elasticmodels.egg-info/dependency_links.txt
elasticmodels.egg-info/not-zip-safe
elasticmodels.egg-info/requires.txt
elasticmodels.egg-info/top_level.txt
elasticmodels/management/__init__.py
elasticmodels/management/commands/__init__.py
elasticmodels/management/commands/rebuild_index.py