Metadata-Version: 1.0
Name: elasticmodels
Version: 0.0.10
Summary: Elasticmodels helps you index and query your Django models using elasticsearch
Home-page: https://github.com/PSU-OIT-ARC/elasticmodels
Author: Matt Johnson
Author-email: mdj2@pdx.edu
License: UNKNOWN
Platform: UNKNOWN
Classifier: Framework :: Django
